pymks/__init__.py
pymks/filter.py
pymks/mks_homogenization_model.py
pymks/mks_localization_model.py
pymks/mks_structure_analysis.py
pymks/stats.py
pymks/tools.py
pymks/bases/__init__.py
pymks/bases/abstract.py
pymks/bases/fourier.py
pymks/bases/gsh.py
pymks/bases/imag_ffts.py
pymks/bases/legendre.py
pymks/bases/primitive.py
pymks/bases/real_ffts.py
pymks/bases/gsh_functions/__init__.py
pymks/bases/gsh_functions/gsh_cub_tri_L0_16.py
pymks/bases/gsh_functions/gsh_hex_tri_L0_16.py
pymks/bases/gsh_functions/gsh_tri_tri_L0_13.py
pymks/datasets/__init__.py
pymks/datasets/base_microstructure_generator.py
pymks/datasets/cahn_hilliard_simulation.py
pymks/datasets/elastic_FE_simulation.py
pymks/datasets/microstructure_generator.py
pymks/datasets/spherical_microstructure_generator.py
pymks/tests/test.py
pymks/tests/test_basis_functions.py
pymks/tests/test_datasets.py
pymks/tests/test_elastic_FE_simulation.py
pymks/tests/test_filter.py
pymks/tests/test_homogenization.py
pymks/tests/test_localization.py
pymks/tests/test_microstructure_generator.py
pymks/tests/test_stats.py
pymks/tests/test_structure_analysis.py
pymks-0.3.3.dist-info/DESCRIPTION.rst
pymks-0.3.3.dist-info/METADATA
pymks-0.3.3.dist-info/RECORD
pymks-0.3.3.dist-info/WHEEL
pymks-0.3.3.dist-info/metadata.json
pymks-0.3.3.dist-info/pbr.json
pymks-0.3.3.dist-info/top_level.txt
