Metadata-Version: 2.0
Name: pymks
Version: 0.3.3
Summary: Materials Knowledge Systems in Python (PyMKS)
Home-page: http://pymks.org
Author: David Brough, Daniel Wheeler
Author-email: david.brough.0416@gmail.com
License: UNKNOWN
Platform: UNKNOWN
